konker_client/__init__.py
konker_client/client.py
konker_client/logging.json
konker_client/mqtt.py
konker_client/request.py
konker_client/system.py
konker_client-0.4.0.dist-info/AUTHORS.rst
konker_client-0.4.0.dist-info/METADATA
konker_client-0.4.0.dist-info/WHEEL
konker_client-0.4.0.dist-info/top_level.txt
konker_client-0.4.0.dist-info/RECORD
